mcp_starter_cli/__init__.py
mcp_starter_cli/main.py
mcp_starter_cli-0.1.0.dist-info/METADATA
mcp_starter_cli-0.1.0.dist-info/WHEEL
mcp_starter_cli-0.1.0.dist-info/top_level.txt
mcp_starter_cli-0.1.0.dist-info/RECORD
