Metadata-Version: 2.4
Name: mcp-starter_cli
Version: 0.1.0
Summary: CLI tool to scaffold, run, and test MCP servers locally with Node
Home-page: https://github.com/Sumedh99/mcp_starter_cli
Author: Sumedh99
Author-email: Sumedh99@users.noreply.github.com
Classifier: Programming Language :: Python :: 3
Classifier: License :: OSI Approved :: MIT License
Classifier: Operating System :: OS Independent
Requires-Python: >=3.7
Dynamic: author
Dynamic: author-email
Dynamic: classifier
Dynamic: description
Dynamic: description-content-type
Dynamic: home-page
Dynamic: requires-python
Dynamic: summary
